[{"title": "达美乐比萨(江汉路步行街店)", "price": 54}, {"title": "TACO AMOR墨西哥餐厅(南京路店)", "price": 105}, {"title": "GAOYUEE高越越西餐(江汉路店)", "price": 97}, {"title": "Table Five魔法欢聚餐厅", "price": 93}, {"title": "夏威驿·国民西餐(江汉路店)", "price": 46}, {"title": "洋食大吉(江汉路店)", "price": 57}, {"title": "阿萨中东料理·清真(江汉路店)", "price": 106}, {"title": "半秋山西餐厅(中山大洋店)", "price": 73}, {"title": "宝岛牛排(江汉路总店)", "price": 57}, {"title": "秀玉coffee&kitchen(新佳丽时尚广场店)", "price": 77}, {"title": "西界stay原切牛排·咖啡西餐厅(江汉路店)", "price": 85}, {"title": "半秋山西餐厅(循礼门南国中心)", "price": 80}, {"title": "超级拌", "price": 22}, {"title": "牧菲客·甄选牛排(Happy站台店)", "price": 49}, {"title": "雨轩主题西餐厅", "price": 73}, {"num": 15, "max": 106, "min": 22, "mean": 71.6}]